{
    "replacement_mode": "Complex",
    "type_replacements": [
        "int",
        "float",
        "str",
        "bool",
        "list",
        "dict",
        "tuple"
    ],
    "ground_truth": [
        {
            "file": "main.py",
            "line_number": 4,
            "col_offset": 5,
            "function": "dec",
            "type": [
                "callable"
            ]
        },
        {
            "file": "main.py",
            "line_number": 4,
            "col_offset": 9,
            "parameter": "f",
            "function": "dec",
            "type": [
                "callable"
            ]
        },
        {
            "file": "main.py",
            "line_number": 5,
            "col_offset": 9,
            "function": "inner",
            "type": [
                "bool"
            ]
        },
        {
            "file": "main.py",
            "line_number": 12,
            "col_offset": 5,
            "function": "func",
            "type": [
                "bool"
            ]
        },
        {
            "file": "main.py",
            "line_number": 16,
            "col_offset": 5,
            "function": "func2",
            "type": [
                "bool"
            ]
        },
        {
            "file": "main.py",
            "line_number": 20,
            "col_offset": 1,
            "variable": "a",
            "type": [
                "bool"
            ]
        }
    ]
}